vt4ai/__init__.py
vt4ai/cli.py
vt4ai/client.py
vt4ai/api/__init__.py
vt4ai/api/auth.py
vt4ai/api/config.py
vt4ai/api/server.py
vt4ai/api/routers/__init__.py
vt4ai/api/routers/domains.py
vt4ai/api/routers/files.py
vt4ai/api/routers/ips.py
vt4ai/api/routers/urls.py
vt4ai/constants/__init__.py
vt4ai/constants/file_relationships.py
vt4ai/constants/output_formats.py
vt4ai/filters/__init__.py
vt4ai/filters/object_attributes_filter.py
vt4ai/mcp/__init__.py
vt4ai/mcp/__main__.py
vt4ai/mcp/config.py
vt4ai/mcp/prompts.py
vt4ai/mcp/server.py
vt4ai/mcp/tools.py
vt4ai/services/__init__.py
vt4ai/services/vt_service.py
vt4ai/templates/__init__.py
vt4ai/templates/templates_loader.py
vt4ai/templates/domains/basic_domain_template.json
vt4ai/templates/files/basic_file_template.json
vt4ai/templates/ips/basic_ip_template.json
vt4ai/templates/urls/basic_url_template.json
vt4ai/utils/__init__.py
vt4ai/utils/json2md.py
vt4ai/utils/json2xml.py
vt4ai-0.1.1.dist-info/licenses/LICENSE
vt4ai-0.1.1.dist-info/METADATA
vt4ai-0.1.1.dist-info/WHEEL
vt4ai-0.1.1.dist-info/top_level.txt
vt4ai-0.1.1.dist-info/RECORD
