Metadata-Version: 2.4
Name: vt4ai
Version: 0.1.1
Summary: This library is a wrapper of vt api in order to use it on AI applications
Author: Alejandro García Peláez
License-Expression: Apache-2.0
Project-URL: Homepage, https://github.com/aleph8/vt4ai
Requires-Python: >=3.11
License-File: LICENSE
Requires-Dist: vt-py==0.21.0
Requires-Dist: pydantic==2.11.7
Requires-Dist: httpx>=0.27.1
Provides-Extra: api
Requires-Dist: fastapi>=0.116.1; extra == "api"
Requires-Dist: uvicorn>=0.35.0; extra == "api"
Provides-Extra: mcp
Requires-Dist: mcp==1.13.0; extra == "mcp"
Dynamic: license-file
